[
  {
    "name": "Dr. Ajay Bhamre",
    "designation": "Pro-VC",
    "university": "Univ. of Mumbai",
    "location": "Mumbai, India"
  },
  {
    "name": "Dr. Chandrahauns R. Chavan",
    "designation": "Director",
    "university": "JBIMS, Churhgate, University of Mumbai",
    "location": "Mumbai, India"
  },
  {
    "name": "Prof. Furqan Qamar",
    "designation": "Former General Secretary General",
    "university": "Association of Indian University",
    "location": "New Delhi, India"
  },
  {
    "name": "Dr. Gajendra K. Vishwakarma",
    "designation": null,
    "university": "Indian School of Mines",
    "location": "Dhanbad, Jharkhand, India"
  },
  {
    "name": "Dr. Ashwini Bhalla",
    "designation": "Professor in Commerce",
    "university": "SCD Govt. College",
    "location": "Ludhiana, India"
  },
  {
    "name": "Dr. G. K. Kalkoti",
    "designation": "Principal",
    "university": "MVM College, (Univ .of Mumbai)",
    "location": "Andheri(W), Mumbai, India"
  },
  {
    "name": "Dr G. V. Bhavani Prasad",
    "designation": "Professor",
    "university": "Kakatiya University",
    "location": "Warangal, Andhra Pradesh, India"
  },
  {
    "name": "Dr. Besavraj Benni",
    "designation": "Chairperson",
    "university": "PG Dept. of Economics, VSK Univ.",
    "location": "Karnataka, India"
  },
  {
    "name": "Dr. M  S Kurhade",
    "designation": "Director",
    "university": "DTSS College of Commerce",
    "location": "Malad (E), Mumbai, India"
  },
  {
    "name": "Dr. G.Y. Shitole",
    "designation": "Principal",
    "university": "Balaji College of Arts, Commerce & Science",
    "location": "Pune, Maharashtra, India"
  },
  {
    "name": "Dr. Mohd. Saeem Khan",
    "designation": null,
    "university": "Dept. of Commerce, Mohammed Ali Jauhar University",
    "location": "Rampur, UP, India"
  },
  {
    "name": "Dr. Michael Rajamathi",
    "designation": "Department of Chemistry",
    "university": "St. Joseph’s College",
    "location": "Bangalore, India"
  },
  {
    "name": "Dr. R. Prabakaran",
    "designation": "Scientific Officer (D)",
    "university": "TIFR",
    "location": "Mumbai, India"
  },
  {
    "name": "Dr. (Mrs.) Masarrat Saheb Ali",
    "designation": null,
    "university": "Govt. of Maharashtra`s S. T. College",
    "location": "Mumbai, India"
  },
  {
    "name": "Dr. Rafat Hussain Rizvi",
    "designation": "Senior Scientist",
    "university": "Washington, U.S.A."
  },
  {
    "name": "Dr. Sachin S. Vernekar",
    "designation": "Dean & Director",
    "university": "BVIMR University, IMED",
    "location": "Pune, India"
  },
  {
    "name": "Dr. Sabir Ali Siddiqui",
    "designation": null,
    "university": "Dhofar University",
    "location": "Sultanate of Oman"
  },
  {
    "name": "Dr. Sayed Hasan Tahir",
    "designation": "Scientist",
    "university": null,
    "location": "California, U.S.A."
  },
  {
    "name": "Dr. Shakeel Ahmed",
    "designation": "Former Director",
    "university": "PIMSE",
    "location": "Pune, India"
  },
  {
    "name": "Dr. Kumar Pankaj",
    "designation": "Director of Arts Faculty",
    "university": "BHU",
    "location": "UP, India"
  },
  {
    "name": "Dr. Ziaul Islam",
    "designation": null,
    "university": "Dept. of Commerce, Aligarh Muslim University",
    "location": "Aligarh, India"
  },
  {
    "name": "Dr. Syed Hasan Mahmud",
    "designation": "Former Professor-Director",
    "university": "UGC-Academic Staff College",
    "location": "Jamia Milia Islamia Univ., New Delhi, India"
  },
  {
    "name": "Dr Syed Iqbal",
    "designation": "Former Head of Department",
    "university": "Burhani College",
    "location": "Mumbai, India"
  },
  {
    "name": "Dr. Rakesh Kumar",
    "designation": "Scientist and Head",
    "university": "NEERI",
    "location": "Mumbai, India"
  },
  {
    "name": "Dr. Sanjay Kaptan",
    "designation": "Former Professor and Head",
    "university": "University of Pune",
    "location": "Pune, India"
  },
  {
    "name": "Dr. Mohammad Khalil Ahmad",
    "designation": "Principal",
    "university": "SEMT A E Kalsekar College (University Of Mumbai)",
    "location": "Nalasopara (West), Palghar, India"
  },
  {
    "name": "Dr. Rafia Shabnum Abedi",
    "designation": "Former HOD",
    "university": "Dept of Urdu, University of Mumbai",
    "location": "Mumbai, India"
  },
  {
    "name": "Dr. M. K. Singh",
    "designation": "Director",
    "university": "MBA, Vinoba Bhave University",
    "location": "Hazaribag, Jharkhand, India"
  },
  {
    "name": "Dr. Sanket Vij",
    "designation": "Chairperson & Director",
    "university": "B.P.S. Women University",
    "location": "Sonipat, India"
  },
  {
    "name": "Dr. Kuldeep Kumar",
    "designation": "Professor",
    "university": "Bond University",
    "location": "Australia"
  }
]